shekan_cli/__init__.py
shekan_cli/cli.py
shekan_cli/config.py
shekan_cli/dns.py
shekan_cli/functions.py
shekan_cli/linux_dns.py
shekan_cli/shekan.py
shekan-0.0.1.dist-info/METADATA
shekan-0.0.1.dist-info/WHEEL
shekan-0.0.1.dist-info/entry_points.txt
shekan-0.0.1.dist-info/top_level.txt
shekan-0.0.1.dist-info/RECORD
